proxyprotocol/__about__.py
proxyprotocol/__init__.py
proxyprotocol/build.py
proxyprotocol/checksum.py
proxyprotocol/detect.py
proxyprotocol/dnsbl.py
proxyprotocol/noop.py
proxyprotocol/py.typed
proxyprotocol/reader.py
proxyprotocol/result.py
proxyprotocol/sock.py
proxyprotocol/tlv.py
proxyprotocol/typing.py
proxyprotocol/v1.py
proxyprotocol/v2.py
proxyprotocol/version.py
proxyprotocol/server/__init__.py
proxyprotocol/server/echo.py
proxyprotocol/server/main.py
proxyprotocol/server/protocol.py
proxy_protocol-0.11.2.dist-info/METADATA
proxy_protocol-0.11.2.dist-info/WHEEL
proxy_protocol-0.11.2.dist-info/entry_points.txt
proxy_protocol-0.11.2.dist-info/licenses/LICENSE.md
proxy_protocol-0.11.2.dist-info/RECORD
