Metadata-Version: 2.1
Name: proxy-protocol
Version: 0.11.2
Summary: PROXY protocol library with asyncio server implementation
Project-URL: Homepage, https://github.com/icgood/proxy-protocol/
Project-URL: API Documentation, https://icgood.github.io/proxy-protocol/
Project-URL: Docker Image, https://github.com/icgood/proxy-protocol/pkgs/container/proxy-protocol
Author-email: Ian Good <ian@icgood.net>
License: ## The MIT License (MIT)
License-File: LICENSE.md
Classifier: Development Status :: 3 - Alpha
Classifier: Intended Audience :: Developers
Classifier: Intended Audience :: Information Technology
Classifier: License :: OSI Approved :: MIT License
Classifier: Programming Language :: Python
Classifier: Programming Language :: Python :: 3.8
Classifier: Programming Language :: Python :: 3.9
Classifier: Programming Language :: Python :: 3.10
Classifier: Programming Language :: Python :: 3.11
Classifier: Programming Language :: Python :: 3.12
Requires-Python: ~=3.8
Requires-Dist: typing-extensions
Provides-Extra: crc32c
Requires-Dist: crc32c~=2.2; extra == 'crc32c'
Provides-Extra: dev
Requires-Dist: autopep8; extra == 'dev'
Requires-Dist: mypy; extra == 'dev'
Requires-Dist: pycodestyle; extra == 'dev'
Requires-Dist: pytest; extra == 'dev'
Requires-Dist: pytest-cov; extra == 'dev'
Requires-Dist: ruff; extra == 'dev'
Provides-Extra: doc
Requires-Dist: cloud-sptheme; extra == 'doc'
Requires-Dist: sphinx; extra == 'doc'
Requires-Dist: sphinx-autodoc-typehints; extra == 'doc'
